maia_test_framework/__init__.py
maia_test_framework/config.py
maia_test_framework/logging_config.py
maia_test_framework/pytest_plugin.py
maia_test_framework/core/__init__.py
maia_test_framework/core/agent.py
maia_test_framework/core/communication_bus.py
maia_test_framework/core/exceptions.py
maia_test_framework/core/judge_agent.py
maia_test_framework/core/message.py
maia_test_framework/core/orchestration_agent.py
maia_test_framework/core/session.py
maia_test_framework/core/mcp/__init__.py
maia_test_framework/core/mcp/base.py
maia_test_framework/core/mcp/remote.py
maia_test_framework/core/mcp/sse.py
maia_test_framework/core/mcp/stub.py
maia_test_framework/core/tools/base.py
maia_test_framework/core/types/judge_result.py
maia_test_framework/core/types/orchestration_policy.py
maia_test_framework/providers/__init__.py
maia_test_framework/providers/base.py
maia_test_framework/providers/crewai.py
maia_test_framework/providers/existing.py
maia_test_framework/providers/generic_lite_llm.py
maia_test_framework/providers/langchain.py
maia_test_framework/providers/litellm_base.py
maia_test_framework/providers/mock.py
maia_test_framework/providers/ollama.py
maia_test_framework/testing/base.py
maia_test_framework/testing/config.py
maia_test_framework/testing/maia_config.py
maia_test_framework/testing/assertions/agents_participation.py
maia_test_framework/testing/assertions/base.py
maia_test_framework/testing/assertions/content_patterns.py
maia_test_framework/testing/mixin/provider_mixin.py
maia_test_framework/testing/validators/agent.py
maia_test_framework/testing/validators/conversation.py
maia_test_framework/testing/validators/performance.py
maia_test_framework/utils/network.py
maia_test_framework-0.9.0.dist-info/METADATA
maia_test_framework-0.9.0.dist-info/WHEEL
maia_test_framework-0.9.0.dist-info/entry_points.txt
maia_test_framework-0.9.0.dist-info/top_level.txt
maia_test_framework-0.9.0.dist-info/RECORD
